<DOMSymbolItem xmlns:xsi="http://www.w3.org/2001/XMLSchema-instance" xmlns="http://ns.adobe.com/xfl/2008/" name="Symbol 1108" itemID="6417dc58-0000117f" lastModified="1679253189">
  <timeline>
    <DOMTimeline name="Symbol 1108">
      <layers>
        <DOMLayer name="Layer_1" color="#E4931B" current="true" isSelected="true">
          <frames>
            <DOMFrame index="0" keyMode="9728">
              <elements>
                <DOMShape isFloating="true">
                  <fills>
                    <FillStyle index="1">
                      <RadialGradient>
                        <matrix>
                          <Matrix a="0.000762939453125" b="0.0025177001953125" c="-0.0027008056640625" d="0.0008087158203125" tx="2.3" ty="2.15"/>
                        </matrix>
                        <GradientEntry color="#009ECA" ratio="0"/>
                        <GradientEntry color="#1C00CA" alpha="0" ratio="1"/>
                      </RadialGradient>
                    </FillStyle>
                  </fills>
                  <edges>
                    <Edge fillStyle1="1" edges="!90 30[95 47 86 64!86 64[77 80 58 85!58 85|23 82!23 82[6 74 1 57!1 57[-4 40 5 24!5 24[15 7 33 2!33 2|68 5!68 5[85 13 90 30"/>
                  </edges>
                </DOMShape>
              </elements>
            </DOMFrame>
          </frames>
        </DOMLayer>
      </layers>
    </DOMTimeline>
  </timeline>
</DOMSymbolItem>